Metadata-Version: 2.1
Name: treecount
Version: 0.0.2
Summary: Utility Package that displays out the Tree Structure of a user-defined directory with their respective file count.
Home-page: https://github.com/rushic24/treecount/
Author: Rushi Chaudhari
Author-email: rushic24@gmail.com
License: UNKNOWN
Platform: UNKNOWN
Classifier: Programming Language :: Python :: 3.5
Classifier: Programming Language :: Python :: 3.6
Classifier: Programming Language :: Python :: 3.7
Classifier: Programming Language :: Python :: 3.8
Classifier: Programming Language :: Python :: 3.9
Classifier: Operating System :: OS Independent
Classifier: License :: OSI Approved :: GNU General Public License v3 (GPLv3)
Classifier: Topic :: Utilities
Classifier: Natural Language :: English
Classifier: Development Status :: 5 - Production/Stable
Classifier: Intended Audience :: Customer Service
Classifier: Intended Audience :: Developers
Classifier: Intended Audience :: End Users/Desktop
Provides-Extra: dev
License-File: LICENSE
